{
  "$id": "https://raw.githubusercontent.com/CeeConnect/DictionnaireJsonSchema/schemas/resource/bar/BAR-EN-109",
  "$schema": "https://raw.githubusercontent.com/CeeConnect/DictionnaireJsonSchema/main/meta-schema.json",
  "title": "BAR-EN-109",
  "type": "object",
  "properties": {
    "batiment": {
      "title": "Logement",
      "type": "object",
      "properties": {
        "anciennete": {
          "$ref": "https://raw.githubusercontent.com/CeeConnect/DictionnaireJsonSchema/main/type/bar/batiment/anciennete.json"
        },
        "type": {
          "$ref": "https://raw.githubusercontent.com/CeeConnect/DictionnaireJsonSchema/main/type/bar/batiment/type.json"
        }
      },
      "required": [
        "anciennete",
        "type"
      ]
    },
    "operation": {
      "title": "Opération",
      "type": "object",
      "properties": {
        "quantite": {
          "title": "Surface de toiture protégée",
          "unit": "m²",
          "$ref": "https://raw.githubusercontent.com/CeeConnect/DictionnaireJsonSchema/main/type/bar/operation/quantite.json"
        }
      },
      "required": [
        "quantite"
      ]
    }
  },
  "required": [
    "batiment",
    "operation"
  ]
}